mesmerize_viz/VERSION
mesmerize_viz/__init__.py
mesmerize_viz/_cnmf.py
mesmerize_viz/_mcorr.py
mesmerize_viz/_utils.py
mesmerize_viz-0.1.0.dist-info/LICENSE
mesmerize_viz-0.1.0.dist-info/METADATA
mesmerize_viz-0.1.0.dist-info/WHEEL
mesmerize_viz-0.1.0.dist-info/top_level.txt
mesmerize_viz-0.1.0.dist-info/RECORD
