Metadata-Version: 2.1
Name: mesmerize-viz
Version: 0.1.0
Summary: Mesmerize visualization package using fastplotlib
Home-page: https://github.com/kushalkolar/mesmerize-viz
Author: Kushal Kolar, Caitlin Lewis
Author-email: 
License: GPL v3.0
Classifier: Programming Language :: Python :: 3
Classifier: License :: OSI Approved :: Apache Software License
Classifier: Operating System :: POSIX :: Linux
Classifier: Operating System :: MacOS :: MacOS X
Classifier: Operating System :: Microsoft :: Windows :: Windows 10
Classifier: Topic :: Scientific/Engineering :: Bio-Informatics
Classifier: Topic :: Scientific/Engineering :: Image Recognition
Classifier: Topic :: Scientific/Engineering :: Information Analysis
Classifier: Intended Audience :: Science/Research
License-File: LICENSE
Requires-Dist: fastplotlib[notebook] ==0.1.0a16
Requires-Dist: pygfx ==0.1.17
Requires-Dist: ipydatagrid
Requires-Dist: tslearn
